[{"icon":"gray","text":"Java HashSet"},{"icon":"gray","text":"Java While Loop"},{"icon":"gray","text":"Java Variables"},{"icon":"gray","text":"Java Operators"},{"icon":"gray","text":"Java Methods"},{"icon":"gray","text":"Java Output / Print"},{"icon":"gray","text":"Java Identifiers"},{"icon":"gray","text":"Java Else"},{"icon":"gray","text":"Java Break and Continue"},{"icon":"gray","text":"Java Do/While Loop"},{"icon":"gray","text":"Java Scope"},{"icon":"gray","text":"Operators"},{"icon":"gray","text":"Java Switch"},{"icon":"gray","text":"Java Threads"},{"icon":"gray","text":"Java OOP"},{"icon":"gray","text":"Java HashMap"},{"icon":"gray","text":"Java Method Parameters"},{"icon":"gray","text":"Java Return"},{"icon":"gray","text":"Java Abstraction"},{"icon":"gray","text":"Java Exceptions"},{"icon":"gray","text":"Java Data Types"},{"icon":"gray","text":"Strings"},{"icon":"gray","text":"Java Modifiers"},{"icon":"gray","text":"Java Print Variables"},{"icon":"gray","text":"Java ArrayList"},{"icon":"gray","text":"Java For Loop"},{"icon":"gray","text":"Java Encapsulation"},{"icon":"gray","text":"Java Strings"},{"icon":"gray","text":"Java Recursion"},{"icon":"gray","text":"Java Lambda Expressions"},{"icon":"gray","text":"Java Comments"},{"icon":"gray","text":"Java Non-Primitive Data Types"},{"icon":"gray","text":"Java Polymorphism"},{"icon":"gray","text":"Java Inner Classes"},{"icon":"gray","text":"Java User Input"},{"icon":"gray","text":"Java Declare Multiple Variables"},{"icon":"gray","text":"Java Iterator"},{"icon":"gray","text":"Java Boolean Data Types"},{"icon":"gray","text":"Java Classes and Objects"},{"icon":"gray","text":"Java LinkedList"},{"icon":"gray","text":"Java Class Methods"},{"icon":"gray","text":"Java Packages"},{"icon":"gray","text":" Non-Primitive Data Types"},{"icon":"gray","text":"Java Else If"},{"icon":"gray","text":"Print Numbers"},{"icon":"gray","text":"Java Syntax"},{"icon":"gray","text":"Java Characters"},{"icon":"gray","text":"Java Constructors"},{"icon":"gray","text":"Accessing Attributes"},{"icon":"gray","text":"Java Enums"},{"icon":"green","text":"Java Introduction"},{"icon":"gray","text":"Java Numbers"},{"icon":"gray","text":"Java Arrays"},{"icon":"gray","text":"Java Method Overloading"},{"icon":"gray","text":"Java Date and Time"},{"icon":"gray","text":"Test"}]